metodos/__init__.py
metodos/metodos.py
metodos-0.1.0.dist-info/METADATA
metodos-0.1.0.dist-info/WHEEL
metodos-0.1.0.dist-info/top_level.txt
metodos-0.1.0.dist-info/RECORD
