Metadata-Version: 2.4
Name: metodos
Version: 0.1.0
Summary: Solución de sistemas de ecuaciones por métodos numéricos
Author: PC12028
Requires-Python: >=3.6
Requires-Dist: numpy
Dynamic: author
Dynamic: requires-dist
Dynamic: requires-python
Dynamic: summary
